sql_field_report/__init__.py
sql_field_report/__main__.py
sql_field_report/constants/__init__.py
sql_field_report/constants/datatypes.py
sql_field_report/constants/field_report_schema.py
sql_field_report/constants/illegal_chars.py
sql_field_report/sql_field_report.py
sql_field_report/utils/__init__.py
sql_field_report/utils/analysis.py
sql_field_report/utils/databases.py
sql_field_report/utils/excel.py
sql_field_report/utils/file_utils.py
sql_field_report-1.2.7.dist-info/LICENSE
sql_field_report-1.2.7.dist-info/METADATA
sql_field_report-1.2.7.dist-info/WHEEL
sql_field_report-1.2.7.dist-info/entry_points.txt
sql_field_report-1.2.7.dist-info/RECORD
