Metadata-Version: 2.1
Name: sql-field-report
Version: 1.2.7
Summary: 
Author: Will James
Author-email: willj@dealcloud.com
Requires-Python: >=3.9,<4.0
Classifier: Programming Language :: Python :: 3
Classifier: Programming Language :: Python :: 3.9
Classifier: Programming Language :: Python :: 3.10
Classifier: Programming Language :: Python :: 3.11
Requires-Dist: coloredlogs (>=15.0.1,<16.0.0)
Requires-Dist: connectorx (>=0.3.3,<0.4.0)
Requires-Dist: faust-cchardet (>=2.1.18,<3.0.0)
Requires-Dist: mysql-connector-python (>=8.0.33,<9.0.0)
Requires-Dist: openpyxl (>=3.1.2,<4.0.0)
Requires-Dist: pandas (>=2.1.1,<3.0.0)
Requires-Dist: polars (>=0.20,<0.21)
Requires-Dist: pyarrow (>=16.1,<17.0)
Requires-Dist: pyodbc (>=5.1.0,<6.0.0)
Requires-Dist: pytest (>=8.2,<9.0)
Requires-Dist: python-dotenv (>=1.0.0,<2.0.0)
Requires-Dist: regex (>=2024.5,<2025.0)
Requires-Dist: sqlalchemy (>=2.0.11,<3.0.0)
Requires-Dist: typer[all] (>=0.12.0,<0.13.0)
Requires-Dist: xlsx2csv (>=0.8.1,<0.9.0)
